favicons/__init__.py
favicons/_cli/__init__.py
favicons/_cli/main.py
favicons/_constants.py
favicons/_exceptions.py
favicons/_generate.py
favicons/_types/__init__.py
favicons/_types/color.py
favicons/_types/properties.py
favicons/_util.py
favicons/cli.py
favicons/py.typed
favicons-0.2.2.dist-info/LICENSE
favicons-0.2.2.dist-info/METADATA
favicons-0.2.2.dist-info/WHEEL
favicons-0.2.2.dist-info/entry_points.txt
favicons-0.2.2.dist-info/RECORD
