Metadata-Version: 2.1
Name: favicons
Version: 0.2.2
Summary: Favicon generator for Python 3 with strongly typed sync & async APIs, CLI, & HTML generation.
Home-page: https://github.com/thatmattlove/favicons
License: BSD-3-Clause-Clear
Author: Matt Love
Author-email: matt@hyperglass.dev
Requires-Python: >=3.10.0,<4.0
Classifier: Development Status :: 4 - Beta
Classifier: License :: Other/Proprietary License
Classifier: Programming Language :: Python :: 3
Classifier: Programming Language :: Python :: 3.10
Classifier: Programming Language :: Python :: 3.11
Classifier: Programming Language :: Python :: 3.12
Classifier: Topic :: Internet :: WWW/HTTP
Classifier: Topic :: Multimedia :: Graphics :: Graphics Conversion
Classifier: Topic :: Software Development :: Libraries :: Python Modules
Classifier: Topic :: Software Development :: User Interfaces
Classifier: Typing :: Typed
Requires-Dist: pillow (>=10.2.0,<11.0.0)
Requires-Dist: reportlab (>=4.1.0,<5.0.0)
Requires-Dist: rich (>=13.7.0,<14.0.0)
Requires-Dist: rlpycairo (>=0.3.0,<0.4.0)
Requires-Dist: svglib (>=1.5.1,<2.0.0)
Requires-Dist: typer (>=0.9.0,<0.10.0)
Project-URL: Repository, https://github.com/thatmattlove/favicons
